wonterfact/__init__.py
wonterfact/buds.py
wonterfact/core_nodes.py
wonterfact/cupy_utils.py
wonterfact/examples/conv_nmf.py
wonterfact/examples/nmf.py
wonterfact/examples/snmf.py
wonterfact/glob_var_manager.py
wonterfact/graphviz.py
wonterfact/leaves.py
wonterfact/observers.py
wonterfact/operators.py
wonterfact/root.py
wonterfact/utils.py
wonterfact-3.0.0.dist-info/WHEEL
wonterfact-3.0.0.dist-info/METADATA
wonterfact-3.0.0.dist-info/RECORD
