Metadata-Version: 2.1
Name: wonterfact
Version: 3.0.0
Summary: A powerful tool to design any tensor factorization model and estimate the corresponding parameters
Home-page: https://github.com/smartimpulse/wonterfact
License: GPL-3.0-or-later
Keywords: tensor,factorization,IA,signal,bayes
Author: Smart-Impulse
Author-email: contact@smart-impulse.com
Requires-Python: >=3.8,<3.10
Classifier: Intended Audience :: Developers
Classifier: Intended Audience :: Education
Classifier: Intended Audience :: Information Technology
Classifier: Intended Audience :: Science/Research
Classifier: License :: OSI Approved :: GNU General Public License v3 or later (GPLv3+)
Classifier: License :: OSI Approved :: GNU Lesser General Public License v3 or later (LGPLv3+)
Classifier: Operating System :: OS Independent
Classifier: Programming Language :: Python :: 3
Classifier: Programming Language :: Python :: 3 :: Only
Classifier: Programming Language :: Python :: 3.8
Classifier: Programming Language :: Python :: 3.9
Classifier: Topic :: Scientific/Engineering
Classifier: Topic :: Scientific/Engineering :: Artificial Intelligence
Classifier: Topic :: Scientific/Engineering :: Information Analysis
Classifier: Topic :: Scientific/Engineering :: Mathematics
Classifier: Topic :: Software Development
Classifier: Topic :: Software Development :: Libraries
Classifier: Topic :: Software Development :: Libraries :: Python Modules
Classifier: Topic :: Utilities
Requires-Dist: custom_inherit (>=2.3.1)
Requires-Dist: graphviz (>=0.16)
Requires-Dist: methodtools (>=0.4.2)
Requires-Dist: numba (>=0.53.1)
Requires-Dist: numpy (>=1.20.2)
Requires-Dist: opt_einsum (>=3.3.0)
Requires-Dist: python-baseconv (>=1.2.2)
Requires-Dist: scipy (>=1.6.2)
Project-URL: Repository, https://github.com/smartimpulse/wonterfact
